LICENSE.txt
MANIFEST.in
README.md
setup.cfg
setup.py
lcopt/__init__.py
lcopt/analysis.py
lcopt/bw2_export.py
lcopt/bw2_import.py
lcopt/bw2_utils.py
lcopt/constants.py
lcopt/data_store.py
lcopt/export_disclosure.py
lcopt/export_view.py
lcopt/interact.py
lcopt/io.py
lcopt/mass_balance.py
lcopt/model.py
lcopt/multi_tagged.py
lcopt/parameters.py
lcopt/settings.py
lcopt/settings_gui.py
lcopt/utils.py
lcopt/assets/Ecoinvent3_2_apos.pickle
lcopt/assets/Ecoinvent3_2_consequential.pickle
lcopt/assets/Ecoinvent3_2_cutoff.pickle
lcopt/assets/Ecoinvent3_3_cutoff.pickle
lcopt/assets/Ecoinvent3_4_apos.pickle
lcopt/assets/Ecoinvent3_4_consequential.pickle
lcopt/assets/Ecoinvent3_4_cutoff.pickle
lcopt/assets/biosphere3.pickle
lcopt/assets/ecoinvent3_3.pickle
lcopt/assets/ecoinvent_example.lcopt
lcopt/assets/forwast.pickle
lcopt/assets/forwast_example.lcopt
lcopt/assets/lcopt_icon.ico
lcopt/assets/locations.json
lcopt/bin/lcopt_bw2_setup.py
lcopt/bin/lcopt_bw2_setup_forwast.py
lcopt/bin/lcopt_launcher.py
lcopt/bin/lcopt_settings.py
lcopt/bin/__pycache__/lcopt_launcher.cpython-36.pyc
lcopt/bin/__pycache__/lcopt_settings.cpython-36.pyc
lcopt/static/THIS IS SYMLINKED TO THE NOTEBOOK TEST PATH
lcopt/static/css/analysis.css
lcopt/static/css/function_box.css
lcopt/static/css/mass_flow.css
lcopt/static/css/methods_box.css
lcopt/static/css/parameter_table.css
lcopt/static/css/sandbox.css
lcopt/static/css/search_table.css
lcopt/static/css/selectize_location.css
lcopt/static/css/status.css
lcopt/static/css/style.css
lcopt/static/css/toast.css
lcopt/static/css/treetest.css
lcopt/static/css/typeahead.css
lcopt/static/css/waterfall.css
lcopt/static/css/cdn_cache/Muli-Regular.ttf
lcopt/static/css/cdn_cache/bootstrap-dialog.min.css
lcopt/static/css/cdn_cache/bootstrap-select.min.css
lcopt/static/css/cdn_cache/bootstrap.min.css
lcopt/static/css/cdn_cache/font-awesome.min.css
lcopt/static/css/cdn_cache/jquery-ui.css
lcopt/static/css/cdn_cache/material-icons.css
lcopt_dev.egg-info/PKG-INFO
lcopt_dev.egg-info/SOURCES.txt
lcopt_dev.egg-info/dependency_links.txt
lcopt_dev.egg-info/entry_points.txt
lcopt_dev.egg-info/top_level.txt