Metadata-Version: 1.1
Name: lcopt-dev
Version: 0.4.2
Summary: An interactive tool for creating fully parameterised Life Cycle Assessment (LCA) foreground models
Home-page: https://github.com/pjamesjoyce/lcopt/
Author: P. James Joyce
Author-email: pjamesjoyce@gmail.com
License: Copyright 2017 P. James Joyce
